README.txt
setup.cfg
setup.py
collective/__init__.py
collective.dewslider.egg-info/PKG-INFO
collective.dewslider.egg-info/SOURCES.txt
collective.dewslider.egg-info/dependency_links.txt
collective.dewslider.egg-info/entry_points.txt
collective.dewslider.egg-info/namespace_packages.txt
collective.dewslider.egg-info/not-zip-safe
collective.dewslider.egg-info/paster_plugins.txt
collective.dewslider.egg-info/requires.txt
collective.dewslider.egg-info/top_level.txt
collective/dewslider/__init__.py
collective/dewslider/configure.zcml
collective/dewslider/dewslider.swf
collective/dewslider/tests.py
collective/dewslider/example/dewslider.html
collective/dewslider/example/dewslider.xml
collective/dewslider/example/img/1.jpg
collective/dewslider/example/img/2.jpg
collective/dewslider/example/img/3.jpg
collective/dewslider/example/img/4.jpg
collective/dewslider/example/img/5.jpg
collective/dewslider/example/img/6.jpg
docs/HISTORY.txt
docs/INSTALL.txt
docs/LICENSE.GPL
docs/LICENSE.txt