Metadata-Version: 1.0
Name: collective.dewslider
Version: 1.0
Summary: Add dewslider flash slider inside Plone
Home-page: http://svn.plone.org/svn/collective/collective.dewslider
Author: JeanMichel FRANCOIS aka toutpt
Author-email: jeanmichel.francois@makina-corpus.com
License: GPL
Keywords: plone slider photo
Platform: UNKNOWN
Classifier: Framework :: Plone
Classifier: Programming Language :: Python
